[
  {
    "dateOfEntry": {
      "id": 1001,
      "year": {
        "type": 0,
        "limit": 9999
      },
      "month": {
        "type": 0,
        "limit": 12
      },
      "day": {
        "type": 0,
        "limit": 31
      }
    },
    "basicData": {
      "id": 1002,
      "handle": {
        "type": 1,
        "limit": 50
      },
      "pronouns": {
        "type": 1,
        "limit": 50
      },
      "career": {
        "type": 1,
        "limit": 50
      },
      "website": {
        "name": {
          "type": 1,
          "limit": 140
        },
        "url": {
          "type": 1,
          "limit": 280
        }
      }
    },
    "zodiac": {
      "id": 1003,
      "type": 1,
      "limit": 50
    },
    "interest": {
      "id": 1004,
      "type": 1,
      "limit": 280
    },
    "talent": {
      "id": 1005,
      "type": 1,
      "limit": 280
    }
  }
]
